sudachidict_core/__init__.py
sudachidict_core/resources/system.dic
sudachidict_core-20260116.dist-info/licenses/LICENSE-2.0.txt
sudachidict_core-20260116.dist-info/METADATA
sudachidict_core-20260116.dist-info/WHEEL
sudachidict_core-20260116.dist-info/top_level.txt
sudachidict_core-20260116.dist-info/RECORD
