Metadata-Version: 2.4
Name: SudachiDict-core
Version: 20260116
Summary: Sudachi Dictionary for SudachiPy - Core Edition
Home-page: https://github.com/WorksApplications/SudachiDict
Author: Works Applications
Author-email: sudachi@worksap.co.jp
License: Apache-2.0
License-File: LICENSE-2.0.txt
Requires-Dist: SudachiPy<0.7,>=0.5
Dynamic: author
Dynamic: author-email
Dynamic: description
Dynamic: description-content-type
Dynamic: home-page
Dynamic: license
Dynamic: license-file
Dynamic: requires-dist
Dynamic: summary
